setup.py
pytocli/__init__.py
pytocli/_base.py
pytocli.egg-info/PKG-INFO
pytocli.egg-info/SOURCES.txt
pytocli.egg-info/dependency_links.txt
pytocli.egg-info/not-zip-safe
pytocli.egg-info/requires.txt
pytocli.egg-info/top_level.txt