Metadata-Version: 1.1
Name: pytocli
Version: 0.6
Summary: A Python lib to generate CLI commands
Home-page: https://github.com/renzon/pytocli
Author: Renzo Nuccitelli
Author-email: renzo.n@gmail.com
License: BSD
Platform: UNKNOWN
Classifier: Development Status :: 2 - Pre-Alpha
Classifier: Environment :: Console
Classifier: Intended Audience :: Developers
Classifier: License :: OSI Approved :: GNU Affero General Public License v3 or later (AGPLv3+)
Classifier: Operating System :: OS Independent
Classifier: Programming Language :: Python
Classifier: Topic :: Software Development :: Libraries
